MANIFEST.in
README.md
setup.py
skidmarks.py
skidmarks.egg-info/PKG-INFO
skidmarks.egg-info/SOURCES.txt
skidmarks.egg-info/dependency_links.txt
skidmarks.egg-info/not-zip-safe
skidmarks.egg-info/top_level.txt