Metadata-Version: 1.1
Name: skidmarks
Version: 0.0.6
Summary: find runs (non-randomness) in sequences
Home-page: http://github.com/brentp/skidmarks/
Author: brentp
Author-email: bpederse@gmail.com
License: MIT
Keywords: bioinformatics sequence randomness test
Platform: UNKNOWN
Classifier: Programming Language :: Python :: 3
Classifier: Programming Language :: Python :: 2
Classifier: Topic :: Scientific/Engineering :: Bio-Informatics
